taskiq_postgresql/__init__.py
taskiq_postgresql/broker.py
taskiq_postgresql/exceptions.py
taskiq_postgresql/py.typed
taskiq_postgresql/result_backend.py
taskiq_postgresql/scheduler_source.py
taskiq_postgresql/abc/__init__.py
taskiq_postgresql/abc/driver.py
taskiq_postgresql/abc/query.py
taskiq_postgresql/drivers/__init__.py
taskiq_postgresql/drivers/_asyncpg.py
taskiq_postgresql/drivers/_psqlpy.py
taskiq_postgresql/drivers/_psycopg.py
taskiq_postgresql/utils/__init__.py
taskiq_postgresql/utils/get_db_driver.py
taskiq_postgresql/utils/get_db_listen_driver.py
taskiq_postgresql/utils/libs_available.py
taskiq_postgresql-0.4.0.dist-info/METADATA
taskiq_postgresql-0.4.0.dist-info/WHEEL
taskiq_postgresql-0.4.0.dist-info/RECORD
