Metadata-Version: 2.4
Name: taskiq-postgresql
Version: 0.4.0
Summary: PostgreSQL integration for taskiq
Author-email: jeffersonsilva-mb <jefferson.silva@mb.com.br>, Jefferson Venceslau <jeff.venceslau@gmail.com>
License-Expression: MIT
Keywords: async,asyncpg,distributed,postgresql,psqlpy,psycopg3,taskiq,tasks
Classifier: Development Status :: 5 - Production/Stable
Classifier: Framework :: AsyncIO
Classifier: Intended Audience :: Developers
Classifier: Intended Audience :: Information Technology
Classifier: License :: OSI Approved :: MIT License
Classifier: Operating System :: OS Independent
Classifier: Programming Language :: Python
Classifier: Programming Language :: Python :: 3
Classifier: Programming Language :: Python :: 3 :: Only
Classifier: Programming Language :: Python :: 3.9
Classifier: Programming Language :: Python :: 3.10
Classifier: Programming Language :: Python :: 3.11
Classifier: Programming Language :: Python :: 3.12
Classifier: Programming Language :: Python :: 3.13
Classifier: Programming Language :: Python :: Implementation :: CPython
Classifier: Topic :: Software Development
Classifier: Topic :: Software Development :: Libraries
Classifier: Topic :: Software Development :: Libraries :: Python Modules
Classifier: Topic :: System :: Networking
Classifier: Typing :: Typed
Requires-Python: >=3.9
Requires-Dist: taskiq>=0.11.7
Provides-Extra: asyncpg
Requires-Dist: asyncpg>=0.30.0; extra == 'asyncpg'
Provides-Extra: psqlpy
Requires-Dist: psqlpy>=0.11.3; extra == 'psqlpy'
Provides-Extra: psycopg
Requires-Dist: psycopg[binary,pool]>=3.2.9; extra == 'psycopg'
